dataserv_client/__init__.py
dataserv_client/api.py
dataserv_client/builder.py
dataserv_client/cli.py
dataserv_client/common.py
dataserv_client/deserialize.py
dataserv_client/exceptions.py
dataserv_client/logmessages.py
dataserv_client/messaging.py
dataserv_client/version.py
dataserv_client/control/Thread.py
dataserv_client/control/__init__.py
dataserv_client-2.1.12.data/scripts/dataserv-client
dataserv_client-2.1.12.dist-info/DESCRIPTION.rst
dataserv_client-2.1.12.dist-info/METADATA
dataserv_client-2.1.12.dist-info/RECORD
dataserv_client-2.1.12.dist-info/WHEEL
dataserv_client-2.1.12.dist-info/metadata.json
dataserv_client-2.1.12.dist-info/top_level.txt
tests/__init__.py
tests/test_builder.py
tests/test_client.py
tests/test_deserialize.py
