Metadata-Version: 2.0
Name: dataserv-client
Version: 2.1.12
Summary: Client for storing and auditing data. http://storj.io
Home-page: http://storj.io
Author: Shawn Wilkinson
Author-email: shawn+dataserv-client@storj.io
License: MIT
Platform: UNKNOWN
Classifier: Development Status :: 2 - Pre-Alpha
Classifier: Intended Audience :: Developers
Classifier: License :: OSI Approved :: MIT License
Classifier: Operating System :: OS Independent
Classifier: Programming Language :: Python
Classifier: Programming Language :: Python :: 2
Classifier: Programming Language :: Python :: 2.7
Classifier: Programming Language :: Python :: 3
Classifier: Programming Language :: Python :: 3.3
Classifier: Programming Language :: Python :: 3.4
Classifier: Topic :: Software Development :: Libraries :: Python Modules
Requires-Dist: RandomIO (>=0.2.1)
Requires-Dist: btctxstore (>=4.6.0)
Requires-Dist: future (>=0.15.0)
Requires-Dist: partialhash (>=1.1.0)
Requires-Dist: psutil (>=3.2.2)
Requires-Dist: storjcore (>=0.0.6)
Requires-Dist: storjnode (>=0.0.18)
